setup.py
bin/pyr
pyr/__init__.py
pyr/compiler.py
pyr/console.py
pyr/defaults.py
pyr/shell.py
pyr.egg-info/PKG-INFO
pyr.egg-info/SOURCES.txt
pyr.egg-info/dependency_links.txt
pyr.egg-info/requires.txt
pyr.egg-info/top_level.txt