Metadata-Version: 1.0
Name: pyr
Version: 0.3
Summary: A nicer REPL for Python.
Home-page: https://github.com/zain/pyr
Author: Zain Memon
Author-email: zain@inzain.net
License: UNKNOWN
Platform: UNKNOWN
